{
  "user": [
    {
      "id": "1",
      "name": "marouan",
      "address": "environment street",
      "phone": 21549786,
      "email": "ali@gmail.com",
      "currency": "European Union euro - (EU€)"
    }
  ],
  "menu": [
    {
      "id": "75d0",
      "name": "burger",
      "price": "13"
    },
    {
      "id": "c49d",
      "name": "sandwich",
      "price": "20"
    },
    {
      "id": "70ca",
      "name": "makloub",
      "price": "20"
    },
    {
      "id": "427b",
      "name": "pizza",
      "price": "30"
    }
  ],
  "tables": [
    {
      "id": "f83b",
      "name": "table1",
      "floor": "1",
      "capacity": "5",
      "occupied": true
    },
    {
      "id": "93bf",
      "name": "table2",
      "floor": "2",
      "capacity": "3",
      "occupied": true
    },
    {
      "id": "5172",
      "name": "table3",
      "floor": "1",
      "capacity": "3",
      "occupied": false
    },
    {
      "id": "36b1",
      "name": "table4",
      "floor": "1",
      "capacity": "4",
      "occupied": false
    },
    {
      "id": "957f",
      "name": "table5",
      "floor": "3",
      "capacity": "4",
      "occupied": false
    },
    {
      "id": "b9b2",
      "name": "table6 ",
      "floor": "6",
      "capacity": "4",
      "occupied": false
    },
    {
      "id": "5106",
      "name": "table7",
      "floor": "2",
      "capacity": "4",
      "occupied": false
    },
    {
      "id": "1a3b",
      "name": "table8",
      "floor": "1",
      "capacity": "6",
      "occupied": false
    }
  ],
  "Reservations": [
    {
      "id": "d177",
      "name": "Mr.wissem",
      "personsNumber": "3",
      "tableArray": [
        {
          "id": "f83b",
          "name": "table1",
          "floor": "1",
          "capacity": "5",
          "occupied": false
        }
      ],
      "date": "05/08/2024",
      "time": "19:23 PM"
    }
  ],
  "Current_Orders": [
    {
      "id": "1",
      "name": "Full Dish (Lunch)",
      "table": "T7",
      "quantity": 4,
      "prepared": false
    },
    {
      "id": "2",
      "name": "Full Dish (Lunch)",
      "table": "T9",
      "quantity": 2,
      "prepared": false
    },
    {
      "id": "3",
      "name": "Masala Dosa",
      "table": "T3",
      "quantity": 1,
      "prepared": true
    },
    {
      "id": "4",
      "name": "Paneer Masala",
      "table": "T7",
      "quantity": 2,
      "prepared": false
    },
    {
      "id": "5",
      "name": "Ectra Rotis",
      "table": "T9",
      "quantity": 8,
      "prepared": false
    }
  ],
  "Top_Selling_Items": [
    {
      "id": "1",
      "name": "Full Dish (Lunch)",
      "price": 2.99,
      "quantity": 40,
      "date": "2023/03/21"
    },
    {
      "id": "2",
      "name": "Full Dish (Lunch)",
      "price": 2.99,
      "quantity": 30,
      "date": "2023/03/21"
    },
    {
      "id": "3",
      "name": "Full Dish (Lunch)",
      "price": 2.99,
      "quantity": 20,
      "date": "2023/03/21"
    },
    {
      "id": "4",
      "name": "Full Dish (Lunch)",
      "price": 2.99,
      "quantity": 20,
      "date": "2023/03/21"
    },
    {
      "id": "5",
      "name": "Full Dish (Lunch)",
      "price": 2.99,
      "quantity": 10,
      "date": "2023/03/21"
    },
    {
      "id": "6",
      "name": "Full Dish (Lunch)",
      "price": 2.99,
      "quantity": 10,
      "date": "2023/03/21"
    }
  ],
  "customers": [
    {
      "id": "9683",
      "name": "maher",
      "gender": "Mr.",
      "phone": "256987412",
      "datetime": "05/08/2024, 17:37:50"
    },
    {
      "id": "ac1f",
      "name": "amel",
      "gender": "Mrs.",
      "phone": "1456987562",
      "datetime": "05/08/2024, 17:38:00"
    },
    {
      "id": "925f",
      "name": "wissem",
      "gender": "Mr.",
      "phone": "36258741",
      "datetime": "05/08/2024, 17:38:12"
    },
    {
      "id": "9892",
      "name": "wadyaa",
      "gender": "Mr.",
      "phone": "65789321",
      "datetime": "05/08/2024, 17:38:27"
    },
    {
      "id": "08e6",
      "name": "jack",
      "gender": "Mr.",
      "phone": "25698741",
      "datetime": "05/08/2024, 17:44:39"
    },
    {
      "id": "7148",
      "name": "Lina",
      "gender": "Mrs.",
      "phone": "48987563",
      "datetime": "05/08/2024, 17:44:55"
    }
  ],
  "orders": [
    {
      "id": "9b28",
      "data": [
        {
          "id": "75d0",
          "name": "burger",
          "price": "13",
          "qty": 1,
          "notes": ""
        }
      ],
      "table": "",
      "diningOption": "Dine Out- Delivery",
      "time": "19:03 PM",
      "date": "Aug 5, 2024",
      "customer": "amel"
    },
    {
      "id": "13c2",
      "data": [
        {
          "id": "c49d",
          "name": "sandwich",
          "price": "20",
          "qty": 2,
          "notes": "spicy"
        },
        {
          "id": "427b",
          "name": "pizza",
          "price": "30",
          "qty": 1,
          "notes": ""
        }
      ],
      "table": "table2",
      "diningOption": "Dine in",
      "time": "19:28 PM",
      "date": "Aug 5, 2024",
      "customer": "wadyaa"
    }
  ],
  "invoices": [
    {
      "id": "7f31",
      "data": {
        "id": "9b28",
        "data": [
          {
            "id": "75d0",
            "name": "burger",
            "price": "13",
            "qty": 1,
            "notes": ""
          }
        ],
        "table": "",
        "diningOption": "Dine Out- Delivery",
        "time": "19:03 PM",
        "date": "Aug 5, 2024",
        "customer": "amel"
      }
    },
    {
      "id": "37ef",
      "data": {
        "id": "13c2",
        "data": [
          {
            "id": "c49d",
            "name": "sandwich",
            "price": "20",
            "qty": 2,
            "notes": "spicy"
          },
          {
            "id": "427b",
            "name": "pizza",
            "price": "30",
            "qty": 1,
            "notes": ""
          }
        ],
        "table": "table2",
        "diningOption": "Dine in",
        "time": "19:28 PM",
        "date": "Aug 5, 2024",
        "customer": "wadyaa"
      }
    }
  ]
}